<?xml version="1.0" encoding="utf-8"?>
<clanovi>
  <clan>
    <ime>Držislav</ime>
    <prezime>Držislavić</prezime>
    <email>drzislav@gmail.com</email>
    <broj_mobitela>099-333-3331</broj_mobitela>
    <spol>M</spol>
    <datum_rodenja>1998-06-26</datum_rodenja>
    <datum_pocetka>2023-05-26</datum_pocetka>
    <salji_obavijesti>1</salji_obavijesti>
  </clan>
  <clan>
    <ime>Branimir</ime>
    <prezime>Branimirić</prezime>
    <email>branimir@gmail.com</email>
    <broj_mobitela>099-333-3333</broj_mobitela>
    <spol>M</spol>
    <datum_rodenja>1998-06-11</datum_rodenja>
    <datum_pocetka>2023-05-22</datum_pocetka>
    <salji_obavijesti>0</salji_obavijesti>
  </clan>
  <clan>
    <ime>Sven</ime>
    <prezime>Kucina</prezime>
    <email>sven@gmail.com</email>
    <broj_mobitela>099-242-3333</broj_mobitela>
    <spol>M</spol>
    <datum_rodenja>2002-02-05</datum_rodenja>
    <datum_pocetka>2023-05-03</datum_pocetka>
    <salji_obavijesti>1</salji_obavijesti>
  </clan>
  <clan>
    <ime>Pero</ime>
    <prezime>Perić</prezime>
    <email>pero@gmail.com</email>
    <broj_mobitela>099-222-2222</broj_mobitela>
    <spol>Ž</spol>
    <datum_rodenja>1999-09-10</datum_rodenja>
    <datum_pocetka>2023-05-22</datum_pocetka>
    <salji_obavijesti>0</salji_obavijesti>
  </clan>
  <clan>
    <ime>Ana</ime>
    <prezime>Anić</prezime>
    <email>ana@gmail.com</email>
    <broj_mobitela>099-111-1111</broj_mobitela>
    <spol>Ž</spol>
    <datum_rodenja>1999-09-01</datum_rodenja>
    <datum_pocetka>2023-05-25</datum_pocetka>
    <salji_obavijesti>0</salji_obavijesti>
  </clan>
  <clan>
    <ime>Marko</ime>
    <prezime>Markić</prezime>
    <email>marko@gmail.com</email>
    <broj_mobitela>099-242-3211</broj_mobitela>
    <spol>M</spol>
    <datum_rodenja>2023-05-04</datum_rodenja>
    <datum_pocetka>2023-06-03</datum_pocetka>
    <salji_obavijesti>1</salji_obavijesti>
  </clan>
  <clan>
    <ime>Ratimir</ime>
    <prezime>Ratimirić</prezime>
    <email>ratimir@gmail.com</email>
    <broj_mobitela>099-333-3332</broj_mobitela>
    <spol>M</spol>
    <datum_rodenja>1998-07-11</datum_rodenja>
    <datum_pocetka>2023-05-16</datum_pocetka>
    <salji_obavijesti>0</salji_obavijesti>
  </clan>
  <clan>
    <ime>Trpimir</ime>
    <prezime>Trpimirić</prezime>
    <email>trpimir@gmail.com</email>
    <broj_mobitela>099-333-3335</broj_mobitela>
    <spol>M</spol>
    <datum_rodenja>1998-07-31</datum_rodenja>
    <datum_pocetka>2023-05-16</datum_pocetka>
    <salji_obavijesti>1</salji_obavijesti>
  </clan>
  <clan>
    <ime>Maja</ime>
    <prezime>Majić</prezime>
    <email>maja@gmail.com</email>
    <broj_mobitela>099-333-3337</broj_mobitela>
    <spol>Ž</spol>
    <datum_rodenja>1997-07-08</datum_rodenja>
    <datum_pocetka>2023-05-08</datum_pocetka>
    <salji_obavijesti>1</salji_obavijesti>
  </clan>
  <clan>
    <ime>Mirna</ime>
    <prezime>Mirnić</prezime>
    <email>mirna@gmail.com</email>
    <broj_mobitela>099-333-3338</broj_mobitela>
    <spol>Ž</spol>
    <datum_rodenja>1997-07-25</datum_rodenja>
    <datum_pocetka>2023-05-19</datum_pocetka>
    <salji_obavijesti>0</salji_obavijesti>
  </clan>
  <clan>
    <ime>Ines</ime>
    <prezime>Kucina</prezime>
    <email>ines@gmail.com</email>
    <broj_mobitela>099-111-2222</broj_mobitela>
    <spol>Ž</spol>
    <datum_rodenja>1995-02-08</datum_rodenja>
    <datum_pocetka>2023-05-12</datum_pocetka>
    <salji_obavijesti>0</salji_obavijesti>
  </clan>
  <clan>
    <ime>veredana</ime>
    <prezime>germanis</prezime>
    <email>v@gmail.com</email>
    <broj_mobitela>099-333-3333</broj_mobitela>
    <spol>Ž</spol>
    <datum_rodenja>2023-05-23</datum_rodenja>
    <datum_pocetka>2023-06-01</datum_pocetka>
    <salji_obavijesti>0</salji_obavijesti>
  </clan>
</clanovi>
